{
  "entries": {
    "brew": {
      "bat": {
        "version": "0.15.4",
        "bottle": {
          "cellar": ":any_skip_relocation",
          "prefix": "/usr/local",
          "files": {
            "catalina": {
              "url": "https://homebrew.bintray.com/bottles/bat-0.15.4.catalina.bottle.tar.gz",
              "sha256": "ae2c26d25a0dac35bd839a091f89201b5d9eee32ef613325426c7e8b8812d1a9"
            },
            "mojave": {
              "url": "https://homebrew.bintray.com/bottles/bat-0.15.4.mojave.bottle.tar.gz",
              "sha256": "40dea8577c06a08d3e3bd20a949245ff02ea85153d25f72a65cee03c1b1e1cf9"
            },
            "high_sierra": {
              "url": "https://homebrew.bintray.com/bottles/bat-0.15.4.high_sierra.bottle.tar.gz",
              "sha256": "59bed16f8a4741a9d92f62cb7c9965d1abe40dc5dd2323bc4f37e71330b1abf2"
            }
          }
        }
      },
      "chruby": {
        "version": "0.3.9",
        "bottle": {
          "cellar": ":any_skip_relocation",
          "prefix": "/usr/local",
          "files": {
            "catalina": {
              "url": "https://homebrew.bintray.com/bottles/chruby-0.3.9.catalina.bottle.tar.gz",
              "sha256": "004f825f798a41ffb3c9576aa3b77e7b8cef227287725818f5d3f1a779b12de6"
            },
            "mojave": {
              "url": "https://homebrew.bintray.com/bottles/chruby-0.3.9.mojave.bottle.tar.gz",
              "sha256": "4b3e7d6e76cd5d914b0bb4871a0a0f33c9b997a9c579ca4450191c87c3dc4f53"
            },
            "high_sierra": {
              "url": "https://homebrew.bintray.com/bottles/chruby-0.3.9.high_sierra.bottle.tar.gz",
              "sha256": "d59074fe39429eb9979acd0e81e6b9a142aa73595971cee42ab91bbe850c6105"
            },
            "sierra": {
              "url": "https://homebrew.bintray.com/bottles/chruby-0.3.9.sierra.bottle.tar.gz",
              "sha256": "17dc507695fed71749b5a58152d652bb7b92a4574f200b631a39f5f004e86cca"
            },
            "el_capitan": {
              "url": "https://homebrew.bintray.com/bottles/chruby-0.3.9.el_capitan.bottle.tar.gz",
              "sha256": "ff70dff83817f093d39384a40d3dfb2aaccc1cbe475d58383d4ef157085f2c64"
            },
            "yosemite": {
              "url": "https://homebrew.bintray.com/bottles/chruby-0.3.9.yosemite.bottle.tar.gz",
              "sha256": "eb14810c552b693c5ae82a577be81398e7dfeadc5489666bb0ff89581f09bfe4"
            },
            "mavericks": {
              "url": "https://homebrew.bintray.com/bottles/chruby-0.3.9.mavericks.bottle.tar.gz",
              "sha256": "c7ede5a22e512d3c22406f222b539fe05b78dfb9721cfff8ce94ed0357883ba5"
            }
          }
        }
      },
      "exa": {
        "version": "0.9.0",
        "bottle": {
          "cellar": ":any_skip_relocation",
          "prefix": "/usr/local",
          "files": {
            "catalina": {
              "url": "https://homebrew.bintray.com/bottles/exa-0.9.0.catalina.bottle.tar.gz",
              "sha256": "cc484e7deb12cdae4ede810258be0ca069d7db395897e9d3fbadd501fb075743"
            },
            "mojave": {
              "url": "https://homebrew.bintray.com/bottles/exa-0.9.0.mojave.bottle.tar.gz",
              "sha256": "bc80009ad845d914c08e6de1c39c97e0f4f180ef4f077b3ef1957cab519d6743"
            },
            "high_sierra": {
              "url": "https://homebrew.bintray.com/bottles/exa-0.9.0.high_sierra.bottle.tar.gz",
              "sha256": "7382b758899c756f94c4c99440f71075945d333e302e53139e423fb1798c852e"
            },
            "sierra": {
              "url": "https://homebrew.bintray.com/bottles/exa-0.9.0.sierra.bottle.tar.gz",
              "sha256": "9499359da5f5fffbd8b22c8cb8e78f0fdf99594c4d2b06e7ba58eb21afbcb582"
            }
          }
        }
      },
      "fd": {
        "version": "8.1.1",
        "bottle": {
          "cellar": ":any_skip_relocation",
          "prefix": "/usr/local",
          "files": {
            "catalina": {
              "url": "https://homebrew.bintray.com/bottles/fd-8.1.1.catalina.bottle.tar.gz",
              "sha256": "4625e56da438b94dfe331a2fe1df759b140931241af097df91f29d8ac314f2d3"
            },
            "mojave": {
              "url": "https://homebrew.bintray.com/bottles/fd-8.1.1.mojave.bottle.tar.gz",
              "sha256": "d002e8d8de192b6fad189ff7830d4fe9fc7d4ca9e81aa5ac66bb5200c590703a"
            },
            "high_sierra": {
              "url": "https://homebrew.bintray.com/bottles/fd-8.1.1.high_sierra.bottle.tar.gz",
              "sha256": "c269bbc76090614e7262c81e1b21d784050a71a51a5921686845f0d3c0855400"
            }
          }
        }
      },
      "ffmpeg": {
        "version": "4.3_1",
        "bottle": {
          "cellar": "/usr/local/Cellar",
          "prefix": "/usr/local",
          "files": {
            "catalina": {
              "url": "https://homebrew.bintray.com/bottles/ffmpeg-4.3_1.catalina.bottle.tar.gz",
              "sha256": "5dccea5f0d7ff92fc94e8564d8717f59766ee0db5b8df8a60996e27c57ef3dfc"
            },
            "mojave": {
              "url": "https://homebrew.bintray.com/bottles/ffmpeg-4.3_1.mojave.bottle.tar.gz",
              "sha256": "75b4d5c0639f24f4a49226e7d3d49be35f80ec3680a6d0fdd7d2da4544d366b2"
            },
            "high_sierra": {
              "url": "https://homebrew.bintray.com/bottles/ffmpeg-4.3_1.high_sierra.bottle.tar.gz",
              "sha256": "f4817a0d1cc8675d8785c13a5ea055ff296b241fb1d8a8a1eb301f6a075565b3"
            }
          }
        }
      },
      "fortune": {
        "version": "9708",
        "bottle": {
          "cellar": "/usr/local/Cellar",
          "prefix": "/usr/local",
          "files": {
            "catalina": {
              "url": "https://homebrew.bintray.com/bottles/fortune-9708.catalina.bottle.3.tar.gz",
              "sha256": "bde8e2f3f2e9e65c18b72b647cd8aad7658251592fae03717e7d90f4428464de"
            },
            "mojave": {
              "url": "https://homebrew.bintray.com/bottles/fortune-9708.mojave.bottle.3.tar.gz",
              "sha256": "f635d0fc0504922ba1bfae451f17b874ea96cffb85dead0913adb9da0669738e"
            },
            "high_sierra": {
              "url": "https://homebrew.bintray.com/bottles/fortune-9708.high_sierra.bottle.3.tar.gz",
              "sha256": "b650a61e6b39e9f12179140e0d2b23c0c606e7f29e64851aac5df4e376d77130"
            },
            "sierra": {
              "url": "https://homebrew.bintray.com/bottles/fortune-9708.sierra.bottle.3.tar.gz",
              "sha256": "c6fe1b893c31bc71b2c24de5bcc0a84fbd5025091d796250a7ef4ff6e406eea7"
            }
          }
        }
      },
      "fzf": {
        "version": "0.21.1",
        "bottle": {
          "cellar": ":any_skip_relocation",
          "prefix": "/usr/local",
          "files": {
            "catalina": {
              "url": "https://homebrew.bintray.com/bottles/fzf-0.21.1.catalina.bottle.tar.gz",
              "sha256": "733f79496c3246979ca05eeb5677a5fd9e8ec532e69e8b2012102cacddba8ae6"
            },
            "mojave": {
              "url": "https://homebrew.bintray.com/bottles/fzf-0.21.1.mojave.bottle.tar.gz",
              "sha256": "3c03bb9715be153a0f776d06cf4acd436ad4faa4266f7bd875a0d37594291516"
            },
            "high_sierra": {
              "url": "https://homebrew.bintray.com/bottles/fzf-0.21.1.high_sierra.bottle.tar.gz",
              "sha256": "d15a616156eb92071f1cfc50f10366532af92ca1635d309162141ad67f785865"
            }
          }
        }
      },
      "git": {
        "version": "2.27.0",
        "bottle": {
          "cellar": "/usr/local/Cellar",
          "prefix": "/usr/local",
          "files": {
            "catalina": {
              "url": "https://homebrew.bintray.com/bottles/git-2.27.0.catalina.bottle.tar.gz",
              "sha256": "5bfe46796926e48d2d78ee87e93195c0a36f7c70d9aa4ff8ab77277a6582441a"
            },
            "mojave": {
              "url": "https://homebrew.bintray.com/bottles/git-2.27.0.mojave.bottle.tar.gz",
              "sha256": "dffad4b938672dda3aef783f88cf38d67923f8f8e68df77b198476816fd37d4f"
            },
            "high_sierra": {
              "url": "https://homebrew.bintray.com/bottles/git-2.27.0.high_sierra.bottle.tar.gz",
              "sha256": "c9f1d9ac100e43a2e6f1df9785d98119d08bf144d862fb541c1212ccfb700041"
            }
          }
        }
      },
      "git-delta": {
        "version": "0.1.1",
        "bottle": {
          "cellar": ":any_skip_relocation",
          "prefix": "/usr/local",
          "files": {
            "catalina": {
              "url": "https://homebrew.bintray.com/bottles/git-delta-0.1.1.catalina.bottle.tar.gz",
              "sha256": "2c934142464323e5b0061b633f964acd0fe3b9f87787693c086e3109c24cf4dc"
            },
            "mojave": {
              "url": "https://homebrew.bintray.com/bottles/git-delta-0.1.1.mojave.bottle.tar.gz",
              "sha256": "da93a1dd32a32cf39ef98baedabcc83f041bdb7b0d4721e5304b175dacea4b10"
            },
            "high_sierra": {
              "url": "https://homebrew.bintray.com/bottles/git-delta-0.1.1.high_sierra.bottle.tar.gz",
              "sha256": "9c88edbe0c662fcd99c16789c0de39d25e5537edb74cff26f1929785fb7b70fd"
            }
          }
        }
      },
      "gpg": null,
      "htop-osx": null,
      "hub": {
        "version": "2.14.2",
        "bottle": {
          "cellar": ":any_skip_relocation",
          "prefix": "/usr/local",
          "files": {
            "catalina": {
              "url": "https://homebrew.bintray.com/bottles/hub-2.14.2.catalina.bottle.tar.gz",
              "sha256": "fdf05855839a9d7ec6e7bee6796e3cb5fc473500cffc002366cf98c09a805b69"
            },
            "mojave": {
              "url": "https://homebrew.bintray.com/bottles/hub-2.14.2.mojave.bottle.tar.gz",
              "sha256": "bcbae9c683d76f3395665467ba0f0c00c60c12c84022f72faba4b8981724b563"
            },
            "high_sierra": {
              "url": "https://homebrew.bintray.com/bottles/hub-2.14.2.high_sierra.bottle.tar.gz",
              "sha256": "8800cda4532784bf764ea6116a06c81d8d90bb3d36d8ecf295e64f9dd647c4ad"
            }
          }
        }
      },
      "jq": {
        "version": "1.6",
        "bottle": {
          "cellar": ":any",
          "prefix": "/usr/local",
          "files": {
            "catalina": {
              "url": "https://homebrew.bintray.com/bottles/jq-1.6.catalina.bottle.1.tar.gz",
              "sha256": "820a3c85fcbb63088b160c7edf125d7e55fc2c5c1d51569304499c9cc4b89ce8"
            },
            "mojave": {
              "url": "https://homebrew.bintray.com/bottles/jq-1.6.mojave.bottle.1.tar.gz",
              "sha256": "71f0e76c5b22e5088426c971d5e795fe67abee7af6c2c4ae0cf4c0eb98ed21ff"
            },
            "high_sierra": {
              "url": "https://homebrew.bintray.com/bottles/jq-1.6.high_sierra.bottle.1.tar.gz",
              "sha256": "dffcffa4ea13e8f0f2b45c5121e529077e135ae9a47254c32182231662ee9b72"
            },
            "sierra": {
              "url": "https://homebrew.bintray.com/bottles/jq-1.6.sierra.bottle.1.tar.gz",
              "sha256": "bb4d19dc026c2d72c53eed78eaa0ab982e9fcad2cd2acc6d13e7a12ff658e877"
            }
          }
        }
      },
      "magic-wormhole": {
        "version": "0.12.0",
        "bottle": {
          "cellar": ":any",
          "prefix": "/usr/local",
          "files": {
            "catalina": {
              "url": "https://homebrew.bintray.com/bottles/magic-wormhole-0.12.0.catalina.bottle.tar.gz",
              "sha256": "2a7df1e4f3f866733c53a8dc8c6656eeb4634d57386ba8f75d49656582891225"
            },
            "mojave": {
              "url": "https://homebrew.bintray.com/bottles/magic-wormhole-0.12.0.mojave.bottle.tar.gz",
              "sha256": "8dc8d54c2e161693d905b51710f8111c8d4469c597010f43412f6a169b1318d8"
            },
            "high_sierra": {
              "url": "https://homebrew.bintray.com/bottles/magic-wormhole-0.12.0.high_sierra.bottle.tar.gz",
              "sha256": "3e836c232597424b884bd7cc218bbf0e9c844d13518a3a3af8e3ae190feb788c"
            }
          }
        }
      },
      "nodenv": {
        "version": "1.3.2",
        "bottle": false
      },
      "ponysay": {
        "version": "3.0.3_5",
        "bottle": {
          "cellar": ":any_skip_relocation",
          "prefix": "/usr/local",
          "files": {
            "catalina": {
              "url": "https://homebrew.bintray.com/bottles/ponysay-3.0.3_5.catalina.bottle.tar.gz",
              "sha256": "77e5eb82496f017ceec2250b454b536964aff0609e3ab2a4a785b9d9b62c5393"
            },
            "mojave": {
              "url": "https://homebrew.bintray.com/bottles/ponysay-3.0.3_5.mojave.bottle.tar.gz",
              "sha256": "30dbf5ef6f9aed9feaf26557e8c954eef25102e79c4c8c020d98d25bbb737bab"
            },
            "high_sierra": {
              "url": "https://homebrew.bintray.com/bottles/ponysay-3.0.3_5.high_sierra.bottle.tar.gz",
              "sha256": "78743696032607c87bd59c95f765d6e10f2758be4b152728ae3b9ddbfb16e5cd"
            }
          }
        }
      },
      "postgresql": {
        "version": "12.3_4",
        "bottle": {
          "cellar": "/usr/local/Cellar",
          "prefix": "/usr/local",
          "files": {
            "catalina": {
              "url": "https://homebrew.bintray.com/bottles/postgresql-12.3_4.catalina.bottle.tar.gz",
              "sha256": "069912aa3d10ecb548eb2dddd7e3e1be61d1689d236b5993bce3e1a31811bcd0"
            },
            "mojave": {
              "url": "https://homebrew.bintray.com/bottles/postgresql-12.3_4.mojave.bottle.tar.gz",
              "sha256": "06eb65f3f17b6bf08344cbae35adc295f5c6da22420ee81d1e8fe2787e05a03b"
            },
            "high_sierra": {
              "url": "https://homebrew.bintray.com/bottles/postgresql-12.3_4.high_sierra.bottle.tar.gz",
              "sha256": "93e3b484a26931374ece4ee4f5abd4b3eac0a6e519d2fba696871f2342f0e513"
            }
          }
        },
        "options": {
          "restart_service": "changed"
        }
      },
      "reattach-to-user-namespace": {
        "version": "2.8",
        "bottle": {
          "cellar": ":any_skip_relocation",
          "prefix": "/usr/local",
          "files": {
            "catalina": {
              "url": "https://homebrew.bintray.com/bottles/reattach-to-user-namespace-2.8.catalina.bottle.tar.gz",
              "sha256": "165edabd70a4acbdee2f3e09e9a37e9ca23b2d485ebe12d62511cef9c45fd757"
            },
            "mojave": {
              "url": "https://homebrew.bintray.com/bottles/reattach-to-user-namespace-2.8.mojave.bottle.tar.gz",
              "sha256": "388e45300bf6cf3888a490878c9a03b97c06a52fe316a18d099ab97bddbed295"
            },
            "high_sierra": {
              "url": "https://homebrew.bintray.com/bottles/reattach-to-user-namespace-2.8.high_sierra.bottle.tar.gz",
              "sha256": "adc59ad02ccf302e9c71c08d10a4eb95d5d210dbfebe9a00b41648b094c96f09"
            },
            "sierra": {
              "url": "https://homebrew.bintray.com/bottles/reattach-to-user-namespace-2.8.sierra.bottle.tar.gz",
              "sha256": "1ec537d4be63bbcdaf3644506d0b272051fd2617db84c111152a33d8d0184339"
            }
          }
        }
      },
      "redis": {
        "version": "6.0.5",
        "bottle": {
          "cellar": ":any",
          "prefix": "/usr/local",
          "files": {
            "catalina": {
              "url": "https://homebrew.bintray.com/bottles/redis-6.0.5.catalina.bottle.tar.gz",
              "sha256": "c4c025a3642417b75e69be73cce61f05042107dd52b5f549d9c21eba8d2c2c1c"
            },
            "mojave": {
              "url": "https://homebrew.bintray.com/bottles/redis-6.0.5.mojave.bottle.tar.gz",
              "sha256": "fc2ff703029e0dfceff2ecde31730b3c8766ecac2cac8dd309270c3aa7b417ae"
            },
            "high_sierra": {
              "url": "https://homebrew.bintray.com/bottles/redis-6.0.5.high_sierra.bottle.tar.gz",
              "sha256": "be205c8cecbf8691db5f06b60e9a5dccbfe1e6bef2e1676fe0dbdf109b2fdf9f"
            }
          }
        },
        "options": {
          "restart_service": "changed"
        }
      },
      "ripgrep": {
        "version": "12.1.1",
        "bottle": {
          "cellar": ":any",
          "prefix": "/usr/local",
          "files": {
            "catalina": {
              "url": "https://homebrew.bintray.com/bottles/ripgrep-12.1.1.catalina.bottle.tar.gz",
              "sha256": "60460d422253113af3ed60332104f309638942821c655332211a6bc2213c472c"
            },
            "mojave": {
              "url": "https://homebrew.bintray.com/bottles/ripgrep-12.1.1.mojave.bottle.tar.gz",
              "sha256": "de4b18789f5d9bc4aaa4d906501200ae4ece7a1971dd1b86e2b2d0a2c8e0d764"
            },
            "high_sierra": {
              "url": "https://homebrew.bintray.com/bottles/ripgrep-12.1.1.high_sierra.bottle.tar.gz",
              "sha256": "cfea5335bf4eccfb7cd1d93bec234d96bd49dce8d593ea966687f777909ba291"
            }
          }
        }
      },
      "ruby-install": {
        "version": "0.7.0",
        "bottle": {
          "cellar": ":any_skip_relocation",
          "prefix": "/usr/local",
          "files": {
            "catalina": {
              "url": "https://homebrew.bintray.com/bottles/ruby-install-0.7.0.catalina.bottle.tar.gz",
              "sha256": "8141c3baa93dedadbdeba6d02a0d00ad13493ba052d013807a40ac048617c6da"
            },
            "mojave": {
              "url": "https://homebrew.bintray.com/bottles/ruby-install-0.7.0.mojave.bottle.tar.gz",
              "sha256": "df0319ebf05c4b0700f16b0bd3150f53d3034a4b664d8d10c3f190af266cdbe4"
            },
            "high_sierra": {
              "url": "https://homebrew.bintray.com/bottles/ruby-install-0.7.0.high_sierra.bottle.tar.gz",
              "sha256": "0e88bbe463d29a1e1cc0a91816023346a860a8a08c3daff660c24b313d2b4511"
            },
            "sierra": {
              "url": "https://homebrew.bintray.com/bottles/ruby-install-0.7.0.sierra.bottle.tar.gz",
              "sha256": "0e88bbe463d29a1e1cc0a91816023346a860a8a08c3daff660c24b313d2b4511"
            },
            "el_capitan": {
              "url": "https://homebrew.bintray.com/bottles/ruby-install-0.7.0.el_capitan.bottle.tar.gz",
              "sha256": "0e88bbe463d29a1e1cc0a91816023346a860a8a08c3daff660c24b313d2b4511"
            }
          }
        }
      },
      "source-highlight": {
        "version": "3.1.9_1",
        "bottle": {
          "cellar": "/usr/local/Cellar",
          "prefix": "/usr/local",
          "files": {
            "catalina": {
              "url": "https://homebrew.bintray.com/bottles/source-highlight-3.1.9_1.catalina.bottle.tar.gz",
              "sha256": "fac19971a1a63d2b16842157b4941e61d73a46318633ce185b2ed71df9a5db09"
            },
            "mojave": {
              "url": "https://homebrew.bintray.com/bottles/source-highlight-3.1.9_1.mojave.bottle.tar.gz",
              "sha256": "4459bbef81e9a9d8872bd4ef9ebf5d70620f2723956ae028ce5542288793f753"
            },
            "high_sierra": {
              "url": "https://homebrew.bintray.com/bottles/source-highlight-3.1.9_1.high_sierra.bottle.tar.gz",
              "sha256": "0ea7ec70be5c0e02a211f7079afd181568f2085c0982b1d4bf7a27ceac8f2347"
            }
          }
        }
      },
      "ssh-copy-id": {
        "version": "8.3p1",
        "bottle": false
      },
      "tmux": {
        "version": "3.1b",
        "bottle": {
          "cellar": ":any",
          "prefix": "/usr/local",
          "files": {
            "catalina": {
              "url": "https://homebrew.bintray.com/bottles/tmux-3.1b.catalina.bottle.tar.gz",
              "sha256": "f26bd0c3f5696350dcaf229d0fadaf6ab677c0ebbb550fc499ca0a37da59ab55"
            },
            "mojave": {
              "url": "https://homebrew.bintray.com/bottles/tmux-3.1b.mojave.bottle.tar.gz",
              "sha256": "e9995ca765078be9cfdef4f1b6a628bcded0e96e36649e084a7f5480d165547a"
            },
            "high_sierra": {
              "url": "https://homebrew.bintray.com/bottles/tmux-3.1b.high_sierra.bottle.tar.gz",
              "sha256": "7a04ece8143c0647be18bb14c160a984a5a9f855fa2ee888d21fc19374790ee5"
            }
          }
        }
      },
      "wget": {
        "version": "1.20.3_2",
        "bottle": {
          "cellar": "/usr/local/Cellar",
          "prefix": "/usr/local",
          "files": {
            "catalina": {
              "url": "https://homebrew.bintray.com/bottles/wget-1.20.3_2.catalina.bottle.tar.gz",
              "sha256": "ef65c759c5097a36323fa9c77756468649e8d1980a3a4e05695c05e39568967c"
            },
            "mojave": {
              "url": "https://homebrew.bintray.com/bottles/wget-1.20.3_2.mojave.bottle.tar.gz",
              "sha256": "28f4090610946a4eb207df102d841de23ced0d06ba31cb79e040d883906dcd4f"
            },
            "high_sierra": {
              "url": "https://homebrew.bintray.com/bottles/wget-1.20.3_2.high_sierra.bottle.tar.gz",
              "sha256": "91dd0caca9bd3f38c439d5a7b6f68440c4274945615fae035ff0a369264b8a2f"
            }
          }
        }
      },
      "zsh-autosuggestions": {
        "version": "0.6.4",
        "bottle": false
      },
      "zsh-syntax-highlighting": {
        "version": "0.7.1",
        "bottle": {
          "cellar": ":any_skip_relocation",
          "prefix": "/usr/local",
          "files": {
            "catalina": {
              "url": "https://homebrew.bintray.com/bottles/zsh-syntax-highlighting-0.7.1.catalina.bottle.tar.gz",
              "sha256": "6b7d4cdc41b56c842a4b76f9901d922d1f39bd638e94249881078a873de8970b"
            },
            "mojave": {
              "url": "https://homebrew.bintray.com/bottles/zsh-syntax-highlighting-0.7.1.mojave.bottle.tar.gz",
              "sha256": "6b7d4cdc41b56c842a4b76f9901d922d1f39bd638e94249881078a873de8970b"
            },
            "high_sierra": {
              "url": "https://homebrew.bintray.com/bottles/zsh-syntax-highlighting-0.7.1.high_sierra.bottle.tar.gz",
              "sha256": "6b7d4cdc41b56c842a4b76f9901d922d1f39bd638e94249881078a873de8970b"
            }
          }
        }
      },
      "ajeetdsouza/zoxide/zoxide": null,
      "heroku/brew/heroku": null,
      "indirect/tap/bpb": null,
      "indirect/tap/horse_fortunes": null,
      "nodenv/nodenv/nodenv-package-json-engine": null,
      "romkatv/powerlevel10k/powerlevel10k": null,
      "eth-p/software/bat-extras": null
    },
    "tap": {
      "ajeetdsouza/zoxide": {
        "revision": "e7011f6cb8b7621f7e38a5fe984571c60851918a"
      },
      "heroku/brew": {
        "revision": "2fbdd513b72119e373505ef0c9047a8090cae7d6"
      },
      "indirect/tap": {
        "revision": "f245198a79b64080dab288e6f0709f78376b6267"
      },
      "nodenv/nodenv": {
        "revision": "2ad96de94b7aa4c813f3f331105eb69ca926ae81"
      },
      "romkatv/powerlevel10k": {
        "revision": "06ad7f48760247bbb5fed8b8764e1fdc461ed8a2"
      },
      "eth-p/software": {
        "revision": "83a44aeb53bbd94197ead0531ad14539897d8264"
      }
    },
    "cask": {
      "1password": {
        "version": "7.5",
        "options": {
          "full_name": "1password"
        }
      },
      "acorn": {
        "version": "6.6.1",
        "options": {
          "full_name": "acorn"
        }
      },
      "alfred": {
        "version": "4.0.9_1144",
        "options": {
          "full_name": "alfred"
        }
      },
      "backblaze": {
        "version": "7.0.1.444",
        "options": {
          "full_name": "backblaze"
        }
      },
      "bartender": {
        "version": "3.1.23",
        "options": {
          "full_name": "bartender"
        }
      },
      "bettertouchtool": {
        "version": "3.389-1612",
        "options": {
          "full_name": "bettertouchtool"
        }
      },
      "calibre": {
        "version": "4.19.0",
        "options": {
          "full_name": "calibre"
        }
      },
      "daisydisk": {
        "version": "4.10",
        "options": {
          "full_name": "daisydisk"
        }
      },
      "dash": {
        "version": "5.1.7",
        "options": {
          "full_name": "dash"
        }
      },
      "discord": {
        "version": "0.0.257",
        "options": {
          "full_name": "discord"
        }
      },
      "docker": {
        "version": "2.3.0.3,45519",
        "options": {
          "full_name": "docker"
        }
      },
      "dropbox": {
        "version": "latest",
        "options": {
          "full_name": "dropbox"
        }
      },
      "fantastical": {
        "version": "3.1.1",
        "options": {
          "full_name": "fantastical"
        }
      },
      "firefox": {
        "version": "77.0.1",
        "options": {
          "full_name": "firefox"
        }
      },
      "google-chrome": {
        "version": "83.0.4103.116",
        "options": {
          "full_name": "google-chrome"
        }
      },
      "hammerspoon": {
        "version": "0.9.78",
        "options": {
          "full_name": "hammerspoon"
        }
      },
      "handbrake": {
        "version": "1.3.3",
        "options": {
          "full_name": "handbrake"
        }
      },
      "imageoptim": {
        "version": "1.8.8",
        "options": {
          "full_name": "imageoptim"
        }
      },
      "gitx-gitx": {
        "version": "0.16-2327",
        "options": {
          "full_name": "indirect/tap/gitx-gitx"
        }
      },
      "karabiner-elements": {
        "version": "12.9.0",
        "options": {
          "full_name": "karabiner-elements"
        }
      },
      "keyboard-maestro": {
        "version": "9.0.5",
        "options": {
          "full_name": "keyboard-maestro"
        }
      },
      "kindle": {
        "version": "57029",
        "options": {
          "full_name": "kindle"
        }
      },
      "little-snitch": {
        "version": "4.5.2",
        "options": {
          "full_name": "little-snitch"
        }
      },
      "macvim": {
        "version": "8.2.539,163",
        "options": {
          "full_name": "macvim"
        }
      },
      "marked": {
        "version": "2.5.43,990",
        "options": {
          "full_name": "marked"
        }
      },
      "menumeters": {
        "version": "2.0.7",
        "options": {
          "full_name": "menumeters"
        }
      },
      "name-mangler": {
        "version": "3.6",
        "options": {
          "full_name": "name-mangler"
        }
      },
      "omnifocus": {
        "version": "3.8",
        "options": {
          "full_name": "omnifocus"
        }
      },
      "omnigraffle": {
        "version": "7.16",
        "options": {
          "full_name": "omnigraffle"
        }
      },
      "screens": {
        "version": "4.7.8,25692",
        "options": {
          "full_name": "screens"
        }
      },
      "sequel-pro": {
        "version": "1.1.2",
        "options": {
          "full_name": "sequel-pro"
        }
      },
      "skype": {
        "version": "8.61.0.95",
        "options": {
          "full_name": "skype"
        }
      },
      "slack": {
        "version": "4.6.0",
        "options": {
          "full_name": "slack"
        }
      },
      "soundsource": {
        "version": "4.2.3",
        "options": {
          "full_name": "soundsource"
        }
      },
      "steam": {
        "version": "latest",
        "options": {
          "full_name": "steam"
        }
      },
      "superduper": {
        "version": "3.3.1,121",
        "options": {
          "full_name": "superduper"
        }
      },
      "textmate": {
        "version": "2.0.6",
        "options": {
          "full_name": "textmate"
        }
      },
      "transmit": {
        "version": "5.6.5",
        "options": {
          "full_name": "transmit"
        }
      },
      "vlc": {
        "version": "3.0.11",
        "options": {
          "full_name": "vlc"
        }
      },
      "google-cloud-sdk": {
        "version": "latest",
        "options": {
          "full_name": "google-cloud-sdk"
        }
      },
      "notion": {
        "version": "2.0.7",
        "options": {
          "full_name": "notion"
        }
      }
    },
    "mas": {
      "1Blocker": {
        "id": "1107421413",
        "version": "3.8"
      },
      "Day One": {
        "id": "1055511498",
        "version": "4.15.2"
      },
      "Due": null,
      "GIF Brewery": null,
      "Gapplin": null,
      "Harvest": null,
      "Linea Link": null,
      "Paprika": null,
      "Reeder": null,
      "Simplenote": null,
      "Sip": null,
      "Soulver": null,
      "The Unarchiver": null,
      "Tweetbot": {
        "id": "1384080005",
        "version": "3.3.3"
      },
      "Twitter": {
        "id": "1482454543",
        "version": "8.23"
      },
      "Ulysses": {
        "id": "1225570693",
        "version": "19.2"
      },
      "XScope": null,
      "Instapaper Save for Safari": null
    }
  },
  "system": {
    "macos": {
      "big_sur": {
        "HOMEBREW_VERSION": "2.4.2",
        "HOMEBREW_PREFIX": "/usr/local",
        "Homebrew/homebrew-core": "96eed7401b8a9017c9bc2048c5051896c4ec9539",
        "CLT": "",
        "Xcode": "12.0",
        "macOS": "10.16"
      }
    }
  }
}
